stonegrading/__init__.py
stonegrading/grades.py
stone_grading-0.1.0.dist-info/METADATA
stone_grading-0.1.0.dist-info/WHEEL
stone_grading-0.1.0.dist-info/top_level.txt
stone_grading-0.1.0.dist-info/RECORD
