Metadata-Version: 2.1
Name: stone-grading
Version: 0.1.0
Summary: Diamond Stone Grading Package. It ships stone fields for reports and actual stones
Home-page: UNKNOWN
Author: Gradia Limited
License: MIT
Platform: UNKNOWN
